{"name":"(SC01) Customer can find the product by name.","testSteps":[{"number":1,"description":"Given I am on Home page","duration":25632,"startTime":1435320899897,"screenshots":[{"screenshot":"b4bedbe57fcda7981a3bc07cde63f1a0_NONE.png"}],"result":"SUCCESS","children":[{"number":2,"description":"Open home page","duration":22165,"startTime":1435320900040,"screenshots":[{"screenshot":"b4bedbe57fcda7981a3bc07cde63f1a0_NONE.png"}],"result":"SUCCESS","firstScreenshot":{"screenshot":"b4bedbe57fcda7981a3bc07cde63f1a0_NONE.png"}}],"firstScreenshot":{"screenshot":"b4bedbe57fcda7981a3bc07cde63f1a0_NONE.png"}},{"number":3,"description":"When searching the product by name","duration":22500,"startTime":1435320925530,"screenshots":[{"screenshot":"fa912bc090497d2bdcb7c7e9c7cdf3f1_NONE.png"}],"result":"SUCCESS","children":[{"number":4,"description":"Fill in search field","duration":7902,"startTime":1435320928900,"screenshots":[{"screenshot":"fa912bc090497d2bdcb7c7e9c7cdf3f1_NONE.png"},{"screenshot":"5558abd54301e35faffe6630ff579394_NONE.png"}],"result":"SUCCESS","firstScreenshot":{"screenshot":"fa912bc090497d2bdcb7c7e9c7cdf3f1_NONE.png"}},{"number":5,"description":"Press go button","duration":9988,"startTime":1435320936802,"screenshots":[{"screenshot":"6be882315c9a8a9c20dbe84fe94119a9_NONE.png"},{"screenshot":"156c14b123c056107d6dd023ae0b8fba_NONE.png"}],"result":"SUCCESS","firstScreenshot":{"screenshot":"6be882315c9a8a9c20dbe84fe94119a9_NONE.png"}}],"firstScreenshot":{"screenshot":"fa912bc090497d2bdcb7c7e9c7cdf3f1_NONE.png"}},{"number":6,"description":"Then I see the desired products on Search results page","duration":7480,"startTime":1435320948030,"screenshots":[{"screenshot":"156c14b123c056107d6dd023ae0b8fba_NONE.png"}],"result":"SUCCESS","children":[{"number":7,"description":"Assert on search results page","duration":2530,"startTime":1435320949220,"screenshots":[{"screenshot":"156c14b123c056107d6dd023ae0b8fba_NONE.png"}],"result":"SUCCESS","firstScreenshot":{"screenshot":"156c14b123c056107d6dd023ae0b8fba_NONE.png"}},{"number":8,"description":"Assert products displayed","duration":2560,"startTime":1435320951760,"screenshots":[{"screenshot":"156c14b123c056107d6dd023ae0b8fba_NONE.png"}],"result":"SUCCESS","firstScreenshot":{"screenshot":"156c14b123c056107d6dd023ae0b8fba_NONE.png"}}],"firstScreenshot":{"screenshot":"156c14b123c056107d6dd023ae0b8fba_NONE.png"}}],"userStory":{"id":"Search","storyName":"Search","path":"com/nbty/stories/search/Search.story","type":"story"},"title":"(SC01) Customer can find the product by name.","tags":[{"name":"Search","type":"story"},{"name":"Search/Search","type":"story"}],"startTime":1435320899841,"duration":55679,"manual":false,"result":"SUCCESS"}